pyqsub/__core__.py
pyqsub/__init__.py
pyqsub-1.0.3.dist-info/DESCRIPTION.rst
pyqsub-1.0.3.dist-info/METADATA
pyqsub-1.0.3.dist-info/RECORD
pyqsub-1.0.3.dist-info/WHEEL
pyqsub-1.0.3.dist-info/entry_points.txt
pyqsub-1.0.3.dist-info/metadata.json
pyqsub-1.0.3.dist-info/top_level.txt
