Metadata-Version: 2.0
Name: pyqsub
Version: 1.0.3
Summary: Python module for running jobs on a cluster
Home-page: https://github.com/djpugh/pyqsub
Author: David Pugh
Author-email: djpugh@gmail.com
License: UNKNOWN
Download-URL: https://github.com/djpugh/pyqsub/tarball/v1.0.2
Keywords: cluster,torque,pbs,qsub
Platform: UNKNOWN
